cosa/__init__.py
cosa/config.py
cosa/environment.py
cosa/new_problem.py
cosa/options.py
cosa/problem.py
cosa/representation.py
cosa/shell.py
cosa/analyzers/__init__.py
cosa/analyzers/bmc_ltl.py
cosa/analyzers/bmc_parametric.py
cosa/analyzers/bmc_safety.py
cosa/analyzers/bmc_temporal.py
cosa/analyzers/dispatcher.py
cosa/analyzers/mcsolver.py
cosa/encoders/__init__.py
cosa/encoders/btor2.py
cosa/encoders/clock.py
cosa/encoders/coreir.py
cosa/encoders/explicit_transition_system.py
cosa/encoders/factory.py
cosa/encoders/formulae.py
cosa/encoders/generators.py
cosa/encoders/ltl.py
cosa/encoders/miter.py
cosa/encoders/modules.py
cosa/encoders/parametric_behavior.py
cosa/encoders/sugar.py
cosa/encoders/symbolic_transition_system.py
cosa/encoders/systemverilog_verific.py
cosa/encoders/template.py
cosa/encoders/verilog_hts.py
cosa/encoders/verilog_yosys.py
cosa/modifiers/__init__.py
cosa/modifiers/behavior.py
cosa/modifiers/coi.py
cosa/modifiers/factory.py
cosa/modifiers/model_extension.py
cosa/modifiers/template.py
cosa/printers/__init__.py
cosa/printers/factory.py
cosa/printers/hts.py
cosa/printers/template.py
cosa/printers/trace.py
cosa/utils/__init__.py
cosa/utils/formula_mngm.py
cosa/utils/generic.py
cosa/utils/logger.py
cosa/utils/verilog.py
cosa/walkers/__init__.py
cosa/walkers/verilog_walker.py
CoSA-0.4.dist-info/LICENSE.txt
CoSA-0.4.dist-info/METADATA
CoSA-0.4.dist-info/WHEEL
CoSA-0.4.dist-info/entry_points.txt
CoSA-0.4.dist-info/top_level.txt
CoSA-0.4.dist-info/zip-safe
CoSA-0.4.dist-info/RECORD
