Metadata-Version: 2.1
Name: CoSA
Version: 0.4
Summary: CoreIR Symbolic Analyzer
Home-page: http://github.com/cristian-mattarei/CoSA
Author: Cristian Mattarei
Author-email: cristian.mattarei@gmail.com
License: BSD
Platform: UNKNOWN
Requires-Dist: six
Requires-Dist: pyparsing
Requires-Dist: pysmt
Requires-Dist: coreir
Requires-Dist: hwtypes
